trial_IGNchinmay/__init__.py
trial_IGNchinmay/contour_utils.py
trial_IGNchinmay/draw_utils.py
trial_IGNchinmay/file_utils.py
trial_IGNchinmay/geom_utils.py
trial_IGNchinmay/img_utils.py
trial_IGNchinmay/json_utils.py
trial_IGNchinmay/labelme_utils.py
trial_IGNchinmay/mouse_utils.py
trial_IGNchinmay/multi_process_utils.py
trial_IGNchinmay/show_utils.py
trial_IGNchinmay/system_utils.py
trial_IGNchinmay/transform_utils.py
trial_IGNchinmay/typehint_utils.py
trial_IGNchinmay/video_utils/__init__.py
trial_IGNchinmay/video_utils/dump_frames.py
trial_IGNchinmay/video_utils/exif_utils.py
trial_IGNchinmay/video_utils/folder_reader.py
trial_IGNchinmay/video_utils/play_video.py
trial_IGNchinmay/video_utils/video_reader.py
trial_IGNchinmay/video_utils/video_sync.py
trial_IGNchinmay/video_utils/video_writer.py
trial_IGNchinmay-0.0.14.dist-info/LICENSE
trial_IGNchinmay-0.0.14.dist-info/METADATA
trial_IGNchinmay-0.0.14.dist-info/WHEEL
trial_IGNchinmay-0.0.14.dist-info/top_level.txt
trial_IGNchinmay-0.0.14.dist-info/RECORD
